HISTORY.rst
LICENSE.rst
MANIFEST.in
README.rst
setup.py
src/collective/__init__.py
src/collective.contextimage.egg-info/PKG-INFO
src/collective.contextimage.egg-info/SOURCES.txt
src/collective.contextimage.egg-info/dependency_links.txt
src/collective.contextimage.egg-info/entry_points.txt
src/collective.contextimage.egg-info/namespace_packages.txt
src/collective.contextimage.egg-info/not-zip-safe
src/collective.contextimage.egg-info/requires.txt
src/collective.contextimage.egg-info/top_level.txt
src/collective/contextimage/__init__.py
src/collective/contextimage/configure.zcml
src/collective/contextimage/extender.py
src/collective/contextimage/interfaces.py
src/collective/contextimage/profiles.zcml
src/collective/contextimage/browser/__init__.py
src/collective/contextimage/browser/configure.zcml
src/collective/contextimage/browser/context_footerviewlet.pt
src/collective/contextimage/browser/context_viewlet.pt
src/collective/contextimage/browser/css_viewlet.pt
src/collective/contextimage/browser/logo.pt
src/collective/contextimage/browser/viewlet.py
src/collective/contextimage/profiles/default/browserlayer.xml
src/collective/contextimage/profiles/default/metadata.xml
src/collective/contextimage/profiles/footer/browserlayer.xml
src/collective/contextimage/profiles/footer/metadata.xml
src/collective/contextimage/profiles/footer/rolemap.xml
src/collective/contextimage/profiles/header/browserlayer.xml
src/collective/contextimage/profiles/header/metadata.xml
src/collective/contextimage/profiles/header/rolemap.xml
src/collective/contextimage/profiles/logo/browserlayer.xml
src/collective/contextimage/profiles/logo/metadata.xml
src/collective/contextimage/profiles/logo/rolemap.xml
src/collective/contextimage/profiles/page/browserlayer.xml
src/collective/contextimage/profiles/page/metadata.xml
src/collective/contextimage/profiles/page/rolemap.xml
src/collective/contextimage/profiles/viewlet/browserlayer.xml
src/collective/contextimage/profiles/viewlet/metadata.xml
src/collective/contextimage/profiles/viewlet/rolemap.xml