Metadata-Version: 1.1
Name: collective.contextimage
Version: 1.3.1
Summary: Context sensitive images and markup from extended plone content as viewlet, header, logo, footer, ...
Home-page: http://pypi.python.org/pypi/collective.contextimage
Author: BlueDynamics Alliance
Author-email: dev@bluedynamics.com
License: GPL
Keywords: web zope plone theme viewlet logo header
Platform: UNKNOWN
Classifier: Development Status :: 5 - Production/Stable
Classifier: License :: OSI Approved :: GNU General Public License (GPL)
Classifier: Operating System :: OS Independent
Classifier: Programming Language :: Python
Classifier: Topic :: Software Development
Classifier: Framework :: Plone
Classifier: Framework :: Plone :: 4.1
Classifier: Framework :: Plone :: 4.2
